onevizion/EMail.py
onevizion/Import.py
onevizion/__init__.py
onevizion/curl.py
onevizion/export.py
onevizion/httpbearer.py
onevizion/ovimport.py
onevizion/singleton.py
onevizion/task.py
onevizion/trackor.py
onevizion/util.py
onevizion/workplan.py
onevizion/module/__init__.py
onevizion/module/log.py
onevizion/module/loglevel.py
onevizion/notif/__init__.py
onevizion/notif/queue.py
onevizion/notif/queuerecord.py
onevizion/notif/queuestatus.py
onevizion/notif/service.py
onevizion-1.1.6.dist-info/DESCRIPTION.rst
onevizion-1.1.6.dist-info/METADATA
onevizion-1.1.6.dist-info/RECORD
onevizion-1.1.6.dist-info/WHEEL
onevizion-1.1.6.dist-info/metadata.json
onevizion-1.1.6.dist-info/top_level.txt
